Metadata-Version: 1.1
Name: teme
Version: 0.4
Summary: This module provides easy to use functionalities for sending message from web to telegram.
Home-page: https://github.com/imneonizer/teme
Author: Nitin Rai
Author-email: mneonizer@gmail.com
License: MIT
Download-URL: https://github.com/imneonizer/teme/archive/v0.4.tar.gz
Keywords: web push,message,notify
Platform: UNKNOWN
Classifier: Development Status :: 4 - Beta
Classifier: Intended Audience :: Developers
Classifier: Topic :: Software Development :: Build Tools
Classifier: License :: OSI Approved :: MIT License
Classifier: Programming Language :: Python :: 3
Classifier: Programming Language :: Python :: 3.4
Classifier: Programming Language :: Python :: 3.5
Classifier: Programming Language :: Python :: 3.6
